jolted_cli/__init__.py
jolted_cli/main.py
jolted_cli/tutorial_template.json
jolted_cli/wiki_template.json
jolted_cli-0.1.1.dist-info/METADATA
jolted_cli-0.1.1.dist-info/WHEEL
jolted_cli-0.1.1.dist-info/entry_points.txt
jolted_cli-0.1.1.dist-info/RECORD
